cloudmesh_openstack-4.3.7-py3.8-nspkg.pth
cloudmesh/openstack/__init__.py
cloudmesh/openstack/__version__.py
cloudmesh/openstack/command/__init__.py
cloudmesh/openstack/command/openstack.py
cloudmesh/openstack/compute/Provider.py
cloudmesh/openstack/compute/__init__.py
cloudmesh/openstack/compute/test_openstacksdk.py
cloudmesh_openstack-4.3.7.dist-info/LICENSE
cloudmesh_openstack-4.3.7.dist-info/METADATA
cloudmesh_openstack-4.3.7.dist-info/WHEEL
cloudmesh_openstack-4.3.7.dist-info/namespace_packages.txt
cloudmesh_openstack-4.3.7.dist-info/top_level.txt
cloudmesh_openstack-4.3.7.dist-info/RECORD
